LICENSE
MANIFEST.in
README.md
README.rst
setup.py
django_mailtrail.egg-info/PKG-INFO
django_mailtrail.egg-info/SOURCES.txt
django_mailtrail.egg-info/dependency_links.txt
django_mailtrail.egg-info/top_level.txt
mailtrail/__init__.py
mailtrail/admin.py
mailtrail/models.py
mailtrail/tests.py
mailtrail/utils.py
mailtrail/views.py
mailtrail/backends/__init__.py
mailtrail/backends/base.py
mailtrail/backends/console.py
mailtrail/backends/database.py
mailtrail/backends/filebased.py
mailtrail/backends/smtp.py
mailtrail/migrations/0001_initial.py
mailtrail/migrations/__init__.py
mailtrail/static/style.css
mailtrail/templates/__init__.py
mailtrail/templates/base.html
mailtrail/templates/change.html
mailtrail/templates/change_base.html
mailtrail/templates/email/change.html
mailtrail/templates/email/forward.html
mailtrail/templates/email/raw.html
mailtrail/templates/email/resend.html